{
"tree": {
    "name":      "tree",
    "img_names": ["decor", "tree"],
    "blocked":   true,
    "movable":   true,
    "cost":      20
    },

"bones": {
    "name":      "bones",
    "img_names": ["decor", "bones"],
    "movable":   true,
    "cost":      5
    },

"boxes": {
    "name":      "boxes",
    "img_names": ["decor", "boxes"],
    "blocked":   true,
    "cost":      5
    },

"fire": {
    "name":      "fire",
    "img_names": ["decor", "fire"],
    "blocked":   true,
    "cost":      20
    },

"leafy": {
    "name":      "leafy tree",
    "img_names": ["decor", "leafy"],
    "blocked":   true,
    "movable":   true,
    "rand_X":    0,
    "rand_Y":    2,
    "cost":      25
    },

"skeleton": {
    "name":      "skeleton",
    "img_names": ["decor", "skeleton"],
    "hidden":    true,
    "movable":   false
    },

"shrooms": {
    "name":      "shrooms",
    "img_names": ["decor", "shrooms"],
    "rand_X":    10,
    "rand_Y":    10,
    "cost":      15
    },

"red_plant_left": {
    "name":      "red plant left",
    "img_names": ["decor", "red plant left"],
    "cost":      15
    },

"red_plant_right": {
    "name":      "red plant right",
    "img_names": ["decor", "red plant right"],
    "cost":      15
    },

"cup_shroom": {
    "name":      "cup shroom",
    "img_names": ["decor", "cup shroom"],
    "cost":      15
    },

"frond": {
    "name":      "frond",
    "img_names": ["decor", "frond"],
    "cost":      15
    },

"blades": {
    "name":      "blades",
    "img_names": ["decor", "blades"],
    "hidden":    true,
    "movable":   true,
    "rand_X":    10,
    "rand_Y":    10
    },

"purple_bulbs": {
    "name":      "purple bulbs",
    "img_names": ["decor", "purple bulbs"],
    "hidden":    true,
    "movable":   true,
    "rand_X":    10,
    "rand_Y":    10
    },

"lights": {
    "name":      "lights",
    "img_names": ["decor", "lights"],
    "hidden":    true,
    "rand_X":    5,
    "rand_Y":    5,
    "effect_id": "lamp"
    }
}